{
  "id": "171fab2c-929b-4ddc-8d4b-454f2104e01c",
  "prevId": "400db9e7-780a-44b8-b0be-2db504f59104",
  "version": "7",
  "dialect": "postgresql",
  "tables": {
    "public.category": {
      "name": "category",
      "schema": "",
      "columns": {
        "id": {
          "name": "id",
          "type": "serial",
          "primaryKey": true,
          "notNull": true
        },
        "organization_id": {
          "name": "organization_id",
          "type": "text",
          "primaryKey": false,
          "notNull": true
        },
        "name": {
          "name": "name",
          "type": "text",
          "primaryKey": false,
          "notNull": true
        },
        "updated_at": {
          "name": "updated_at",
          "type": "timestamp",
          "primaryKey": false,
          "notNull": true,
          "default": "now()"
        },
        "created_at": {
          "name": "created_at",
          "type": "timestamp",
          "primaryKey": false,
          "notNull": true,
          "default": "now()"
        }
      },
      "indexes": {},
      "foreignKeys": {},
      "compositePrimaryKeys": {},
      "uniqueConstraints": {},
      "checkConstraints": {}
    },
    "public.customer": {
      "name": "customer",
      "schema": "",
      "columns": {
        "id": {
          "name": "id",
          "type": "serial",
          "primaryKey": true,
          "notNull": true
        },
        "organization_id": {
          "name": "organization_id",
          "type": "text",
          "primaryKey": false,
          "notNull": true
        },
        "name": {
          "name": "name",
          "type": "text",
          "primaryKey": false,
          "notNull": true
        },
        "email": {
          "name": "email",
          "type": "text",
          "primaryKey": false,
          "notNull": false
        },
        "whatsapp": {
          "name": "whatsapp",
          "type": "text",
          "primaryKey": false,
          "notNull": false
        },
        "updated_at": {
          "name": "updated_at",
          "type": "timestamp",
          "primaryKey": false,
          "notNull": true,
          "default": "now()"
        },
        "created_at": {
          "name": "created_at",
          "type": "timestamp",
          "primaryKey": false,
          "notNull": true,
          "default": "now()"
        }
      },
      "indexes": {},
      "foreignKeys": {},
      "compositePrimaryKeys": {},
      "uniqueConstraints": {},
      "checkConstraints": {}
    },
    "public.location": {
      "name": "location",
      "schema": "",
      "columns": {
        "id": {
          "name": "id",
          "type": "serial",
          "primaryKey": true,
          "notNull": true
        },
        "organization_id": {
          "name": "organization_id",
          "type": "text",
          "primaryKey": false,
          "notNull": true
        },
        "name": {
          "name": "name",
          "type": "text",
          "primaryKey": false,
          "notNull": true
        },
        "address": {
          "name": "address",
          "type": "text",
          "primaryKey": false,
          "notNull": false
        },
        "is_active": {
          "name": "is_active",
          "type": "boolean",
          "primaryKey": false,
          "notNull": true,
          "default": true
        },
        "updated_at": {
          "name": "updated_at",
          "type": "timestamp",
          "primaryKey": false,
          "notNull": true,
          "default": "now()"
        },
        "created_at": {
          "name": "created_at",
          "type": "timestamp",
          "primaryKey": false,
          "notNull": true,
          "default": "now()"
        }
      },
      "indexes": {},
      "foreignKeys": {},
      "compositePrimaryKeys": {},
      "uniqueConstraints": {},
      "checkConstraints": {}
    },
    "public.organization": {
      "name": "organization",
      "schema": "",
      "columns": {
        "id": {
          "name": "id",
          "type": "text",
          "primaryKey": true,
          "notNull": true
        },
        "stripe_customer_id": {
          "name": "stripe_customer_id",
          "type": "text",
          "primaryKey": false,
          "notNull": false
        },
        "stripe_subscription_id": {
          "name": "stripe_subscription_id",
          "type": "text",
          "primaryKey": false,
          "notNull": false
        },
        "stripe_subscription_price_id": {
          "name": "stripe_subscription_price_id",
          "type": "text",
          "primaryKey": false,
          "notNull": false
        },
        "stripe_subscription_status": {
          "name": "stripe_subscription_status",
          "type": "text",
          "primaryKey": false,
          "notNull": false
        },
        "stripe_subscription_current_period_end": {
          "name": "stripe_subscription_current_period_end",
          "type": "bigint",
          "primaryKey": false,
          "notNull": false
        },
        "updated_at": {
          "name": "updated_at",
          "type": "timestamp",
          "primaryKey": false,
          "notNull": true,
          "default": "now()"
        },
        "created_at": {
          "name": "created_at",
          "type": "timestamp",
          "primaryKey": false,
          "notNull": true,
          "default": "now()"
        }
      },
      "indexes": {
        "stripe_customer_id_idx": {
          "name": "stripe_customer_id_idx",
          "columns": [
            {
              "expression": "stripe_customer_id",
              "isExpression": false,
              "asc": true,
              "nulls": "last"
            }
          ],
          "isUnique": true,
          "concurrently": false,
          "method": "btree",
          "with": {}
        }
      },
      "foreignKeys": {},
      "compositePrimaryKeys": {},
      "uniqueConstraints": {},
      "checkConstraints": {}
    },
    "public.product_location": {
      "name": "product_location",
      "schema": "",
      "columns": {
        "id": {
          "name": "id",
          "type": "serial",
          "primaryKey": true,
          "notNull": true
        },
        "product_id": {
          "name": "product_id",
          "type": "integer",
          "primaryKey": false,
          "notNull": true
        },
        "location_id": {
          "name": "location_id",
          "type": "integer",
          "primaryKey": false,
          "notNull": true
        },
        "price": {
          "name": "price",
          "type": "numeric(10, 2)",
          "primaryKey": false,
          "notNull": false
        },
        "is_active": {
          "name": "is_active",
          "type": "boolean",
          "primaryKey": false,
          "notNull": true,
          "default": true
        },
        "updated_at": {
          "name": "updated_at",
          "type": "timestamp",
          "primaryKey": false,
          "notNull": true,
          "default": "now()"
        },
        "created_at": {
          "name": "created_at",
          "type": "timestamp",
          "primaryKey": false,
          "notNull": true,
          "default": "now()"
        }
      },
      "indexes": {
        "product_location_idx": {
          "name": "product_location_idx",
          "columns": [
            {
              "expression": "product_id",
              "isExpression": false,
              "asc": true,
              "nulls": "last"
            },
            {
              "expression": "location_id",
              "isExpression": false,
              "asc": true,
              "nulls": "last"
            }
          ],
          "isUnique": true,
          "concurrently": false,
          "method": "btree",
          "with": {}
        }
      },
      "foreignKeys": {
        "product_location_product_id_product_id_fk": {
          "name": "product_location_product_id_product_id_fk",
          "tableFrom": "product_location",
          "tableTo": "product",
          "columnsFrom": [
            "product_id"
          ],
          "columnsTo": [
            "id"
          ],
          "onDelete": "cascade",
          "onUpdate": "no action"
        },
        "product_location_location_id_location_id_fk": {
          "name": "product_location_location_id_location_id_fk",
          "tableFrom": "product_location",
          "tableTo": "location",
          "columnsFrom": [
            "location_id"
          ],
          "columnsTo": [
            "id"
          ],
          "onDelete": "cascade",
          "onUpdate": "no action"
        }
      },
      "compositePrimaryKeys": {},
      "uniqueConstraints": {},
      "checkConstraints": {}
    },
    "public.product": {
      "name": "product",
      "schema": "",
      "columns": {
        "id": {
          "name": "id",
          "type": "serial",
          "primaryKey": true,
          "notNull": true
        },
        "organization_id": {
          "name": "organization_id",
          "type": "text",
          "primaryKey": false,
          "notNull": true
        },
        "category_id": {
          "name": "category_id",
          "type": "integer",
          "primaryKey": false,
          "notNull": false
        },
        "name": {
          "name": "name",
          "type": "text",
          "primaryKey": false,
          "notNull": true
        },
        "description": {
          "name": "description",
          "type": "text",
          "primaryKey": false,
          "notNull": false
        },
        "price": {
          "name": "price",
          "type": "numeric(10, 2)",
          "primaryKey": false,
          "notNull": true
        },
        "cost_price": {
          "name": "cost_price",
          "type": "numeric(10, 2)",
          "primaryKey": false,
          "notNull": false
        },
        "sku": {
          "name": "sku",
          "type": "text",
          "primaryKey": false,
          "notNull": false
        },
        "image_url": {
          "name": "image_url",
          "type": "text",
          "primaryKey": false,
          "notNull": false
        },
        "is_active": {
          "name": "is_active",
          "type": "boolean",
          "primaryKey": false,
          "notNull": true,
          "default": true
        },
        "updated_at": {
          "name": "updated_at",
          "type": "timestamp",
          "primaryKey": false,
          "notNull": true,
          "default": "now()"
        },
        "created_at": {
          "name": "created_at",
          "type": "timestamp",
          "primaryKey": false,
          "notNull": true,
          "default": "now()"
        }
      },
      "indexes": {},
      "foreignKeys": {
        "product_category_id_category_id_fk": {
          "name": "product_category_id_category_id_fk",
          "tableFrom": "product",
          "tableTo": "category",
          "columnsFrom": [
            "category_id"
          ],
          "columnsTo": [
            "id"
          ],
          "onDelete": "set null",
          "onUpdate": "no action"
        }
      },
      "compositePrimaryKeys": {},
      "uniqueConstraints": {},
      "checkConstraints": {}
    },
    "public.sale_item": {
      "name": "sale_item",
      "schema": "",
      "columns": {
        "id": {
          "name": "id",
          "type": "serial",
          "primaryKey": true,
          "notNull": true
        },
        "sale_id": {
          "name": "sale_id",
          "type": "integer",
          "primaryKey": false,
          "notNull": true
        },
        "product_id": {
          "name": "product_id",
          "type": "integer",
          "primaryKey": false,
          "notNull": false
        },
        "product_name": {
          "name": "product_name",
          "type": "text",
          "primaryKey": false,
          "notNull": true
        },
        "quantity": {
          "name": "quantity",
          "type": "integer",
          "primaryKey": false,
          "notNull": true
        },
        "unit_price": {
          "name": "unit_price",
          "type": "numeric(10, 2)",
          "primaryKey": false,
          "notNull": true
        },
        "subtotal": {
          "name": "subtotal",
          "type": "numeric(10, 2)",
          "primaryKey": false,
          "notNull": true
        },
        "created_at": {
          "name": "created_at",
          "type": "timestamp",
          "primaryKey": false,
          "notNull": true,
          "default": "now()"
        }
      },
      "indexes": {},
      "foreignKeys": {
        "sale_item_sale_id_sale_id_fk": {
          "name": "sale_item_sale_id_sale_id_fk",
          "tableFrom": "sale_item",
          "tableTo": "sale",
          "columnsFrom": [
            "sale_id"
          ],
          "columnsTo": [
            "id"
          ],
          "onDelete": "cascade",
          "onUpdate": "no action"
        },
        "sale_item_product_id_product_id_fk": {
          "name": "sale_item_product_id_product_id_fk",
          "tableFrom": "sale_item",
          "tableTo": "product",
          "columnsFrom": [
            "product_id"
          ],
          "columnsTo": [
            "id"
          ],
          "onDelete": "set null",
          "onUpdate": "no action"
        }
      },
      "compositePrimaryKeys": {},
      "uniqueConstraints": {},
      "checkConstraints": {}
    },
    "public.sale": {
      "name": "sale",
      "schema": "",
      "columns": {
        "id": {
          "name": "id",
          "type": "serial",
          "primaryKey": true,
          "notNull": true
        },
        "receipt_number": {
          "name": "receipt_number",
          "type": "text",
          "primaryKey": false,
          "notNull": true
        },
        "organization_id": {
          "name": "organization_id",
          "type": "text",
          "primaryKey": false,
          "notNull": true
        },
        "location_id": {
          "name": "location_id",
          "type": "integer",
          "primaryKey": false,
          "notNull": true
        },
        "user_id": {
          "name": "user_id",
          "type": "text",
          "primaryKey": false,
          "notNull": true
        },
        "customer_id": {
          "name": "customer_id",
          "type": "integer",
          "primaryKey": false,
          "notNull": false
        },
        "customer_name": {
          "name": "customer_name",
          "type": "text",
          "primaryKey": false,
          "notNull": true
        },
        "customer_email": {
          "name": "customer_email",
          "type": "text",
          "primaryKey": false,
          "notNull": false
        },
        "customer_whatsapp": {
          "name": "customer_whatsapp",
          "type": "text",
          "primaryKey": false,
          "notNull": false
        },
        "payment_method": {
          "name": "payment_method",
          "type": "payment_method",
          "typeSchema": "public",
          "primaryKey": false,
          "notNull": true
        },
        "total": {
          "name": "total",
          "type": "numeric(10, 2)",
          "primaryKey": false,
          "notNull": true
        },
        "status": {
          "name": "status",
          "type": "sale_status",
          "typeSchema": "public",
          "primaryKey": false,
          "notNull": true,
          "default": "'completed'"
        },
        "updated_at": {
          "name": "updated_at",
          "type": "timestamp",
          "primaryKey": false,
          "notNull": true,
          "default": "now()"
        },
        "created_at": {
          "name": "created_at",
          "type": "timestamp",
          "primaryKey": false,
          "notNull": true,
          "default": "now()"
        }
      },
      "indexes": {},
      "foreignKeys": {
        "sale_location_id_location_id_fk": {
          "name": "sale_location_id_location_id_fk",
          "tableFrom": "sale",
          "tableTo": "location",
          "columnsFrom": [
            "location_id"
          ],
          "columnsTo": [
            "id"
          ],
          "onDelete": "no action",
          "onUpdate": "no action"
        },
        "sale_customer_id_customer_id_fk": {
          "name": "sale_customer_id_customer_id_fk",
          "tableFrom": "sale",
          "tableTo": "customer",
          "columnsFrom": [
            "customer_id"
          ],
          "columnsTo": [
            "id"
          ],
          "onDelete": "set null",
          "onUpdate": "no action"
        }
      },
      "compositePrimaryKeys": {},
      "uniqueConstraints": {},
      "checkConstraints": {}
    },
    "public.stock_movement": {
      "name": "stock_movement",
      "schema": "",
      "columns": {
        "id": {
          "name": "id",
          "type": "serial",
          "primaryKey": true,
          "notNull": true
        },
        "stock_id": {
          "name": "stock_id",
          "type": "integer",
          "primaryKey": false,
          "notNull": true
        },
        "type": {
          "name": "type",
          "type": "stock_movement_type",
          "typeSchema": "public",
          "primaryKey": false,
          "notNull": true
        },
        "quantity": {
          "name": "quantity",
          "type": "integer",
          "primaryKey": false,
          "notNull": true
        },
        "reason": {
          "name": "reason",
          "type": "stock_movement_reason",
          "typeSchema": "public",
          "primaryKey": false,
          "notNull": true
        },
        "user_id": {
          "name": "user_id",
          "type": "text",
          "primaryKey": false,
          "notNull": true
        },
        "notes": {
          "name": "notes",
          "type": "text",
          "primaryKey": false,
          "notNull": false
        },
        "created_at": {
          "name": "created_at",
          "type": "timestamp",
          "primaryKey": false,
          "notNull": true,
          "default": "now()"
        }
      },
      "indexes": {},
      "foreignKeys": {
        "stock_movement_stock_id_stock_id_fk": {
          "name": "stock_movement_stock_id_stock_id_fk",
          "tableFrom": "stock_movement",
          "tableTo": "stock",
          "columnsFrom": [
            "stock_id"
          ],
          "columnsTo": [
            "id"
          ],
          "onDelete": "cascade",
          "onUpdate": "no action"
        }
      },
      "compositePrimaryKeys": {},
      "uniqueConstraints": {},
      "checkConstraints": {}
    },
    "public.stock": {
      "name": "stock",
      "schema": "",
      "columns": {
        "id": {
          "name": "id",
          "type": "serial",
          "primaryKey": true,
          "notNull": true
        },
        "product_id": {
          "name": "product_id",
          "type": "integer",
          "primaryKey": false,
          "notNull": true
        },
        "location_id": {
          "name": "location_id",
          "type": "integer",
          "primaryKey": false,
          "notNull": true
        },
        "quantity": {
          "name": "quantity",
          "type": "integer",
          "primaryKey": false,
          "notNull": true,
          "default": 0
        },
        "low_stock_threshold": {
          "name": "low_stock_threshold",
          "type": "integer",
          "primaryKey": false,
          "notNull": true,
          "default": 5
        },
        "updated_at": {
          "name": "updated_at",
          "type": "timestamp",
          "primaryKey": false,
          "notNull": true,
          "default": "now()"
        },
        "created_at": {
          "name": "created_at",
          "type": "timestamp",
          "primaryKey": false,
          "notNull": true,
          "default": "now()"
        }
      },
      "indexes": {
        "stock_product_location_idx": {
          "name": "stock_product_location_idx",
          "columns": [
            {
              "expression": "product_id",
              "isExpression": false,
              "asc": true,
              "nulls": "last"
            },
            {
              "expression": "location_id",
              "isExpression": false,
              "asc": true,
              "nulls": "last"
            }
          ],
          "isUnique": true,
          "concurrently": false,
          "method": "btree",
          "with": {}
        }
      },
      "foreignKeys": {
        "stock_product_id_product_id_fk": {
          "name": "stock_product_id_product_id_fk",
          "tableFrom": "stock",
          "tableTo": "product",
          "columnsFrom": [
            "product_id"
          ],
          "columnsTo": [
            "id"
          ],
          "onDelete": "cascade",
          "onUpdate": "no action"
        },
        "stock_location_id_location_id_fk": {
          "name": "stock_location_id_location_id_fk",
          "tableFrom": "stock",
          "tableTo": "location",
          "columnsFrom": [
            "location_id"
          ],
          "columnsTo": [
            "id"
          ],
          "onDelete": "cascade",
          "onUpdate": "no action"
        }
      },
      "compositePrimaryKeys": {},
      "uniqueConstraints": {},
      "checkConstraints": {}
    },
    "public.todo": {
      "name": "todo",
      "schema": "",
      "columns": {
        "id": {
          "name": "id",
          "type": "serial",
          "primaryKey": true,
          "notNull": true
        },
        "owner_id": {
          "name": "owner_id",
          "type": "text",
          "primaryKey": false,
          "notNull": true
        },
        "title": {
          "name": "title",
          "type": "text",
          "primaryKey": false,
          "notNull": true
        },
        "message": {
          "name": "message",
          "type": "text",
          "primaryKey": false,
          "notNull": true
        },
        "updated_at": {
          "name": "updated_at",
          "type": "timestamp",
          "primaryKey": false,
          "notNull": true,
          "default": "now()"
        },
        "created_at": {
          "name": "created_at",
          "type": "timestamp",
          "primaryKey": false,
          "notNull": true,
          "default": "now()"
        }
      },
      "indexes": {},
      "foreignKeys": {},
      "compositePrimaryKeys": {},
      "uniqueConstraints": {},
      "checkConstraints": {}
    },
    "public.user_location": {
      "name": "user_location",
      "schema": "",
      "columns": {
        "id": {
          "name": "id",
          "type": "serial",
          "primaryKey": true,
          "notNull": true
        },
        "user_id": {
          "name": "user_id",
          "type": "text",
          "primaryKey": false,
          "notNull": true
        },
        "location_id": {
          "name": "location_id",
          "type": "integer",
          "primaryKey": false,
          "notNull": true
        },
        "created_at": {
          "name": "created_at",
          "type": "timestamp",
          "primaryKey": false,
          "notNull": true,
          "default": "now()"
        }
      },
      "indexes": {},
      "foreignKeys": {
        "user_location_location_id_location_id_fk": {
          "name": "user_location_location_id_location_id_fk",
          "tableFrom": "user_location",
          "tableTo": "location",
          "columnsFrom": [
            "location_id"
          ],
          "columnsTo": [
            "id"
          ],
          "onDelete": "cascade",
          "onUpdate": "no action"
        }
      },
      "compositePrimaryKeys": {},
      "uniqueConstraints": {},
      "checkConstraints": {}
    }
  },
  "enums": {
    "public.payment_method": {
      "name": "payment_method",
      "schema": "public",
      "values": [
        "cash",
        "debit",
        "credit",
        "transfer"
      ]
    },
    "public.sale_status": {
      "name": "sale_status",
      "schema": "public",
      "values": [
        "completed",
        "cancelled"
      ]
    },
    "public.stock_movement_reason": {
      "name": "stock_movement_reason",
      "schema": "public",
      "values": [
        "purchase",
        "adjustment",
        "return",
        "loss",
        "breakage",
        "sale"
      ]
    },
    "public.stock_movement_type": {
      "name": "stock_movement_type",
      "schema": "public",
      "values": [
        "in",
        "out"
      ]
    }
  },
  "schemas": {},
  "sequences": {},
  "views": {},
  "_meta": {
    "columns": {},
    "schemas": {},
    "tables": {}
  }
}